fastsrm/__init__.py
fastsrm/check_inputs.py
fastsrm/fastsrm.py
fastsrm/identifiable_srm.py
fastsrm/srm.py
fastsrm/utils.py
fastsrm-0.0.5.dist-info/LICENSE
fastsrm-0.0.5.dist-info/METADATA
fastsrm-0.0.5.dist-info/WHEEL
fastsrm-0.0.5.dist-info/top_level.txt
fastsrm-0.0.5.dist-info/RECORD
