Metadata-Version: 2.1
Name: fastsrm
Version: 0.0.5
Summary: Fast Shared Response Model
Home-page: https://github.com/hugorichard/FastSRM
Download-URL: https://github.com/hugorichard/FastSRM/archive/v_004.tar.gz
Author: Hugo RICHARD
Author-email: hugo.richard@inria.fr
License: MIT
Keywords: Component analysis,fMRI
Requires-Python: >=3
License-File: LICENSE
Requires-Dist: scipy (>=0.18.0)
Requires-Dist: numpy (>=1.12)
Requires-Dist: scikit-learn (>=0.23)
Requires-Dist: joblib (>=1.1.0)
Requires-Dist: matplotlib (>=2.0.0)
Requires-Dist: pytest (>=6.2.5)
